IbmDeveloperworksQuanbuWenzhangDierBufen/README.md
IbmDeveloperworksQuanbuWenzhangDierBufen/__init__.py
IbmDeveloperworksQuanbuWenzhangDierBufen/__main__.py
IbmDeveloperworksQuanbuWenzhangDierBufen/file.epub
IbmDeveloperworksQuanbuWenzhangDierBufen/index.html
IbmDeveloperworksQuanbuWenzhangDierBufen/css/__init__.py
IbmDeveloperworksQuanbuWenzhangDierBufen/css/annotations.css
IbmDeveloperworksQuanbuWenzhangDierBufen/css/main.css
IbmDeveloperworksQuanbuWenzhangDierBufen/css/normalize.css
IbmDeveloperworksQuanbuWenzhangDierBufen/css/popup.css
IbmDeveloperworksQuanbuWenzhangDierBufen/font/__init__.py
IbmDeveloperworksQuanbuWenzhangDierBufen/font/fontello.eot
IbmDeveloperworksQuanbuWenzhangDierBufen/font/fontello.svg
IbmDeveloperworksQuanbuWenzhangDierBufen/font/fontello.ttf
IbmDeveloperworksQuanbuWenzhangDierBufen/font/fontello.woff
IbmDeveloperworksQuanbuWenzhangDierBufen/img/__init__.py
IbmDeveloperworksQuanbuWenzhangDierBufen/img/annotator-glyph-sprite.png
IbmDeveloperworksQuanbuWenzhangDierBufen/img/annotator-icon-sprite.png
IbmDeveloperworksQuanbuWenzhangDierBufen/img/apple-touch-icon.png
IbmDeveloperworksQuanbuWenzhangDierBufen/img/cancelfullscreen.png
IbmDeveloperworksQuanbuWenzhangDierBufen/img/close.png
IbmDeveloperworksQuanbuWenzhangDierBufen/img/fullscreen.png
IbmDeveloperworksQuanbuWenzhangDierBufen/img/loader.gif
IbmDeveloperworksQuanbuWenzhangDierBufen/img/menu-icon.png
IbmDeveloperworksQuanbuWenzhangDierBufen/img/save.png
IbmDeveloperworksQuanbuWenzhangDierBufen/img/saved.png
IbmDeveloperworksQuanbuWenzhangDierBufen/img/settings-s.png
IbmDeveloperworksQuanbuWenzhangDierBufen/img/settings.png
IbmDeveloperworksQuanbuWenzhangDierBufen/img/star.png
IbmDeveloperworksQuanbuWenzhangDierBufen/js/__init__.py
IbmDeveloperworksQuanbuWenzhangDierBufen/js/epub.js
IbmDeveloperworksQuanbuWenzhangDierBufen/js/epub.min.js
IbmDeveloperworksQuanbuWenzhangDierBufen/js/epub.min.map
IbmDeveloperworksQuanbuWenzhangDierBufen/js/hooks.min.js
ibm_developerworks_quanbu_wenzhang_dier_bufen-2024.3.5.0.dist-info/METADATA
ibm_developerworks_quanbu_wenzhang_dier_bufen-2024.3.5.0.dist-info/WHEEL
ibm_developerworks_quanbu_wenzhang_dier_bufen-2024.3.5.0.dist-info/entry_points.txt
ibm_developerworks_quanbu_wenzhang_dier_bufen-2024.3.5.0.dist-info/top_level.txt
ibm_developerworks_quanbu_wenzhang_dier_bufen-2024.3.5.0.dist-info/RECORD
